tierkreis/__init__.py
tierkreis/_version.py
tierkreis/aer_worker.py
tierkreis/builder.py
tierkreis/codegen.py
tierkreis/consts.py
tierkreis/exceptions.py
tierkreis/executor.py
tierkreis/hpc.py
tierkreis/labels.py
tierkreis/models.py
tierkreis/namespace.py
tierkreis/nexus_worker.py
tierkreis/py.typed
tierkreis/pytket_worker.py
tierkreis/qulacs_worker.py
tierkreis/storage.py
tierkreis/value.py
tierkreis/builtins/__init__.py
tierkreis/builtins/main.py
tierkreis/builtins/stubs.py
tierkreis/cli/__init__.py
tierkreis/cli/run_workflow.py
tierkreis/cli/tkr.py
tierkreis/controller/__init__.py
tierkreis/controller/consts.py
tierkreis/controller/start.py
tierkreis/controller/data/__init__.py
tierkreis/controller/data/core.py
tierkreis/controller/data/graph.py
tierkreis/controller/data/location.py
tierkreis/controller/data/models.py
tierkreis/controller/data/types.py
tierkreis/controller/executor/__init__.py
tierkreis/controller/executor/in_memory_executor.py
tierkreis/controller/executor/multiple.py
tierkreis/controller/executor/protocol.py
tierkreis/controller/executor/shell_executor.py
tierkreis/controller/executor/stdinout.py
tierkreis/controller/executor/uv_executor.py
tierkreis/controller/executor/hpc/hpc_executor.py
tierkreis/controller/executor/hpc/job_spec.py
tierkreis/controller/executor/hpc/pbs.py
tierkreis/controller/executor/hpc/pjsub.py
tierkreis/controller/executor/hpc/slurm.py
tierkreis/controller/storage/__init__.py
tierkreis/controller/storage/adjacency.py
tierkreis/controller/storage/filestorage.py
tierkreis/controller/storage/graphdata.py
tierkreis/controller/storage/in_memory.py
tierkreis/controller/storage/protocol.py
tierkreis/controller/storage/walk.py
tierkreis/graphs/fold.py
tierkreis/graphs/nexus/submit_poll.py
tierkreis/graphs/simulate/compile_simulate.py
tierkreis/idl/models.py
tierkreis/idl/parser.py
tierkreis/idl/spec.py
tierkreis/idl/type_symbols.py
tierkreis/worker/__init__.py
tierkreis/worker/worker.py
tierkreis/worker/storage/__init__.py
tierkreis-2.0.9.dist-info/METADATA
tierkreis-2.0.9.dist-info/WHEEL
tierkreis-2.0.9.dist-info/entry_points.txt
tierkreis-2.0.9.dist-info/licenses/LICENSE
tierkreis-2.0.9.dist-info/RECORD
