Metadata-Version: 2.4
Name: tierkreis
Version: 2.0.9
Summary: Python client and utilities for tierkreis.
Author-email: Seyon Sivarajah <seyon.sivarajah@quantinuum.com>, Lukas Heidemann <lukas.heidemann@quantinuum.com>, John Children <john.children@quantinuum.com>, Alan Lawrence <alan.lawrence@quantinuum.com>, Matthew Burke <matthew.burke@quantinuum.com>, Philipp Seitz <philipp.seitz@quantinuum.com>
License-File: LICENSE
Requires-Python: >=3.12
Requires-Dist: pydantic~=2.5
